{
 "custom_fields": [
  {
   "_assign": null,
   "_comments": null,
   "_liked_by": null,
   "_user_tags": null,
   "allow_in_quick_entry": 0,
   "allow_on_submit": 0,
   "bold": 0,
   "collapsible": 0,
   "collapsible_depends_on": null,
   "columns": 0,
   "creation": "2023-05-22 12:01:03.949641",
   "default": "Today",
   "depends_on": null,
   "description": null,
   "docstatus": 0,
   "dt": "Stock Entry",
   "fetch_from": null,
   "fetch_if_empty": 0,
   "fieldname": "entry_date",
   "fieldtype": "Date",
   "hidden": 0,
   "hide_border": 0,
   "hide_days": 0,
   "hide_seconds": 0,
   "idx": 5,
   "ignore_user_permissions": 0,
   "ignore_xss_filter": 0,
   "in_global_search": 0,
   "in_list_view": 0,
   "in_preview": 0,
   "in_standard_filter": 0,
   "insert_after": "outgoing_stock_entry",
   "is_system_generated": 0,
   "is_virtual": 0,
   "label": "Entry Date",
   "length": 0,
   "mandatory_depends_on": "eval: doc.stock_entry_type == \"Tank Manufactured\" || doc.stock_entry_type == \"Tank Transferred\"",
   "modified": "2023-05-22 12:01:03.949641",
   "modified_by": "Administrator",
   "module": null,
   "name": "Stock Entry-entry_date",
   "no_copy": 0,
   "non_negative": 0,
   "options": null,
   "owner": "Administrator",
   "permlevel": 0,
   "precision": "",
   "print_hide": 0,
   "print_hide_if_no_value": 0,
   "print_width": null,
   "read_only": 0,
   "read_only_depends_on": null,
   "report_hide": 0,
   "reqd": 0,
   "search_index": 0,
   "sort_options": 0,
   "translatable": 0,
   "unique": 0,
   "width": null
  },
  {
   "_assign": null,
   "_comments": null,
   "_liked_by": null,
   "_user_tags": null,
   "allow_in_quick_entry": 0,
   "allow_on_submit": 0,
   "bold": 0,
   "collapsible": 0,
   "collapsible_depends_on": null,
   "columns": 0,
   "creation": "2023-07-14 18:49:08.286973",
   "default": null,
   "depends_on": "eval:doc.stock_entry_type == \"Geyser Manufactured\"",
   "description": null,
   "docstatus": 0,
   "dt": "Stock Entry",
   "fetch_from": null,
   "fetch_if_empty": 0,
   "fieldname": "production_line",
   "fieldtype": "Link",
   "hidden": 1,
   "hide_border": 0,
   "hide_days": 0,
   "hide_seconds": 0,
   "idx": 7,
   "ignore_user_permissions": 0,
   "ignore_xss_filter": 0,
   "in_global_search": 0,
   "in_list_view": 0,
   "in_preview": 0,
   "in_standard_filter": 0,
   "insert_after": "purpose",
   "is_system_generated": 0,
   "is_virtual": 0,
   "label": "Production Line",
   "length": 0,
   "mandatory_depends_on": "eval:doc.stock_entry_type == \"Geyser Manufactured\"",
   "modified": "2023-07-14 18:49:08.286973",
   "modified_by": "Administrator",
   "module": null,
   "name": "Stock Entry-production_line",
   "no_copy": 0,
   "non_negative": 0,
   "options": "Production Lines",
   "owner": "Administrator",
   "permlevel": 0,
   "precision": "",
   "print_hide": 0,
   "print_hide_if_no_value": 0,
   "print_width": null,
   "read_only": 1,
   "read_only_depends_on": null,
   "report_hide": 0,
   "reqd": 0,
   "search_index": 0,
   "sort_options": 0,
   "translatable": 0,
   "unique": 0,
   "width": null
  },
  {
   "_assign": null,
   "_comments": null,
   "_liked_by": null,
   "_user_tags": null,
   "allow_in_quick_entry": 0,
   "allow_on_submit": 0,
   "bold": 0,
   "collapsible": 0,
   "collapsible_depends_on": null,
   "columns": 0,
   "creation": "2023-07-14 18:49:08.558584",
   "default": null,
   "depends_on": "eval:doc.stock_entry_type == \"Geyser Manufactured\" || doc.stock_entry_type == \"Element Manufactured\"",
   "description": null,
   "docstatus": 0,
   "dt": "Stock Entry",
   "fetch_from": null,
   "fetch_if_empty": 0,
   "fieldname": "worforce",
   "fieldtype": "Int",
   "hidden": 0,
   "hide_border": 0,
   "hide_days": 0,
   "hide_seconds": 0,
   "idx": 8,
   "ignore_user_permissions": 0,
   "ignore_xss_filter": 0,
   "in_global_search": 0,
   "in_list_view": 0,
   "in_preview": 0,
   "in_standard_filter": 0,
   "insert_after": "production_line",
   "is_system_generated": 0,
   "is_virtual": 0,
   "label": "Worforce",
   "length": 0,
   "mandatory_depends_on": "eval:doc.stock_entry_type == \"Geyser Manufactured\" || doc.stock_entry_type == \"Element Manufactured\"",
   "modified": "2023-07-14 18:49:08.558584",
   "modified_by": "Administrator",
   "module": null,
   "name": "Stock Entry-worforce",
   "no_copy": 0,
   "non_negative": 0,
   "options": null,
   "owner": "Administrator",
   "permlevel": 0,
   "precision": "",
   "print_hide": 0,
   "print_hide_if_no_value": 0,
   "print_width": null,
   "read_only": 0,
   "read_only_depends_on": null,
   "report_hide": 0,
   "reqd": 0,
   "search_index": 0,
   "sort_options": 0,
   "translatable": 0,
   "unique": 0,
   "width": null
  },
  {
   "_assign": null,
   "_comments": null,
   "_liked_by": null,
   "_user_tags": null,
   "allow_in_quick_entry": 0,
   "allow_on_submit": 0,
   "bold": 0,
   "collapsible": 0,
   "collapsible_depends_on": null,
   "columns": 0,
   "creation": "2023-07-14 18:49:08.946165",
   "default": null,
   "depends_on": "eval:doc.production_line",
   "description": null,
   "docstatus": 0,
   "dt": "Stock Entry",
   "fetch_from": "production_line.contractor_name",
   "fetch_if_empty": 0,
   "fieldname": "contractor_name",
   "fieldtype": "Data",
   "hidden": 0,
   "hide_border": 0,
   "hide_days": 0,
   "hide_seconds": 0,
   "idx": 9,
   "ignore_user_permissions": 0,
   "ignore_xss_filter": 0,
   "in_global_search": 0,
   "in_list_view": 0,
   "in_preview": 0,
   "in_standard_filter": 0,
   "insert_after": "worforce",
   "is_system_generated": 0,
   "is_virtual": 0,
   "label": "Contractor Name",
   "length": 0,
   "mandatory_depends_on": null,
   "modified": "2023-07-14 18:49:08.946165",
   "modified_by": "Administrator",
   "module": null,
   "name": "Stock Entry-contractor_name",
   "no_copy": 0,
   "non_negative": 0,
   "options": null,
   "owner": "Administrator",
   "permlevel": 0,
   "precision": "",
   "print_hide": 0,
   "print_hide_if_no_value": 0,
   "print_width": null,
   "read_only": 1,
   "read_only_depends_on": null,
   "report_hide": 0,
   "reqd": 0,
   "search_index": 0,
   "sort_options": 0,
   "translatable": 1,
   "unique": 0,
   "width": null
  },
  {
   "_assign": null,
   "_comments": null,
   "_liked_by": null,
   "_user_tags": null,
   "allow_in_quick_entry": 0,
   "allow_on_submit": 0,
   "bold": 0,
   "collapsible": 0,
   "collapsible_depends_on": null,
   "columns": 0,
   "creation": "2023-07-15 15:15:53.686493",
   "default": "",
   "depends_on": null,
   "description": null,
   "docstatus": 0,
   "dt": "Stock Entry",
   "fetch_from": null,
   "fetch_if_empty": 0,
   "fieldname": "production_entry",
   "fieldtype": "Link",
   "hidden": 1,
   "hide_border": 0,
   "hide_days": 0,
   "hide_seconds": 0,
   "idx": 10,
   "ignore_user_permissions": 0,
   "ignore_xss_filter": 0,
   "in_global_search": 0,
   "in_list_view": 0,
   "in_preview": 0,
   "in_standard_filter": 0,
   "insert_after": "contractor_name",
   "is_system_generated": 0,
   "is_virtual": 0,
   "label": "Production Entry",
   "length": 0,
   "mandatory_depends_on": null,
   "modified": "2023-07-15 15:15:53.686493",
   "modified_by": "Administrator",
   "module": null,
   "name": "Stock Entry-production_entry",
   "no_copy": 0,
   "non_negative": 0,
   "options": "Geyser Production Entry",
   "owner": "Administrator",
   "permlevel": 0,
   "precision": "",
   "print_hide": 0,
   "print_hide_if_no_value": 0,
   "print_width": null,
   "read_only": 0,
   "read_only_depends_on": null,
   "report_hide": 0,
   "reqd": 0,
   "search_index": 0,
   "sort_options": 0,
   "translatable": 0,
   "unique": 0,
   "width": null
  },
  {
   "_assign": null,
   "_comments": null,
   "_liked_by": null,
   "_user_tags": null,
   "allow_in_quick_entry": 0,
   "allow_on_submit": 1,
   "bold": 0,
   "collapsible": 0,
   "collapsible_depends_on": null,
   "columns": 0,
   "creation": "2023-08-02 10:28:47.877283",
   "default": null,
   "depends_on": null,
   "description": null,
   "docstatus": 0,
   "dt": "Stock Entry",
   "fetch_from": null,
   "fetch_if_empty": 0,
   "fieldname": "element_production_entry",
   "fieldtype": "Link",
   "hidden": 1,
   "hide_border": 0,
   "hide_days": 0,
   "hide_seconds": 0,
   "idx": 11,
   "ignore_user_permissions": 0,
   "ignore_xss_filter": 0,
   "in_global_search": 0,
   "in_list_view": 0,
   "in_preview": 0,
   "in_standard_filter": 0,
   "insert_after": "production_entry",
   "is_system_generated": 0,
   "is_virtual": 0,
   "label": "Element Production Entry",
   "length": 0,
   "mandatory_depends_on": null,
   "modified": "2023-08-02 10:28:47.877283",
   "modified_by": "Administrator",
   "module": null,
   "name": "Stock Entry-element_production_entry",
   "no_copy": 0,
   "non_negative": 0,
   "options": "Element Production Entry",
   "owner": "Administrator",
   "permlevel": 0,
   "precision": "",
   "print_hide": 0,
   "print_hide_if_no_value": 0,
   "print_width": null,
   "read_only": 0,
   "read_only_depends_on": null,
   "report_hide": 0,
   "reqd": 0,
   "search_index": 0,
   "sort_options": 0,
   "translatable": 0,
   "unique": 0,
   "width": null
  },
  {
   "_assign": null,
   "_comments": null,
   "_liked_by": null,
   "_user_tags": null,
   "allow_in_quick_entry": 0,
   "allow_on_submit": 1,
   "bold": 0,
   "collapsible": 0,
   "collapsible_depends_on": null,
   "columns": 0,
   "creation": "2023-08-02 10:28:48.187046",
   "default": null,
   "depends_on": null,
   "description": null,
   "docstatus": 0,
   "dt": "Stock Entry",
   "fetch_from": null,
   "fetch_if_empty": 0,
   "fieldname": "element_entry",
   "fieldtype": "Link",
   "hidden": 1,
   "hide_border": 0,
   "hide_days": 0,
   "hide_seconds": 0,
   "idx": 12,
   "ignore_user_permissions": 0,
   "ignore_xss_filter": 0,
   "in_global_search": 0,
   "in_list_view": 0,
   "in_preview": 0,
   "in_standard_filter": 0,
   "insert_after": "element_production_entry",
   "is_system_generated": 0,
   "is_virtual": 0,
   "label": "Element Entry",
   "length": 0,
   "mandatory_depends_on": null,
   "modified": "2023-08-02 10:28:48.187046",
   "modified_by": "Administrator",
   "module": null,
   "name": "Stock Entry-element_entry",
   "no_copy": 0,
   "non_negative": 0,
   "options": "Element Entry",
   "owner": "Administrator",
   "permlevel": 0,
   "precision": "",
   "print_hide": 0,
   "print_hide_if_no_value": 0,
   "print_width": null,
   "read_only": 0,
   "read_only_depends_on": null,
   "report_hide": 0,
   "reqd": 0,
   "search_index": 0,
   "sort_options": 0,
   "translatable": 0,
   "unique": 0,
   "width": null
  },
  {
   "_assign": null,
   "_comments": null,
   "_liked_by": null,
   "_user_tags": null,
   "allow_in_quick_entry": 0,
   "allow_on_submit": 0,
   "bold": 0,
   "collapsible": 0,
   "collapsible_depends_on": null,
   "columns": 0,
   "creation": "2023-08-14 13:40:24.489307",
   "default": null,
   "depends_on": null,
   "description": null,
   "docstatus": 0,
   "dt": "Stock Entry",
   "fetch_from": null,
   "fetch_if_empty": 0,
   "fieldname": "geyser_brand_changing_entry",
   "fieldtype": "Link",
   "hidden": 1,
   "hide_border": 0,
   "hide_days": 0,
   "hide_seconds": 0,
   "idx": 13,
   "ignore_user_permissions": 0,
   "ignore_xss_filter": 0,
   "in_global_search": 0,
   "in_list_view": 0,
   "in_preview": 0,
   "in_standard_filter": 0,
   "insert_after": "element_entry",
   "is_system_generated": 0,
   "is_virtual": 0,
   "label": "Geyser Brand Changing Entry",
   "length": 0,
   "mandatory_depends_on": null,
   "modified": "2023-08-14 13:40:24.489307",
   "modified_by": "Administrator",
   "module": null,
   "name": "Stock Entry-geyser_brand_changing_entry",
   "no_copy": 0,
   "non_negative": 0,
   "options": "Geyser Brand Changing Entry",
   "owner": "Administrator",
   "permlevel": 0,
   "precision": "",
   "print_hide": 0,
   "print_hide_if_no_value": 0,
   "print_width": null,
   "read_only": 0,
   "read_only_depends_on": null,
   "report_hide": 0,
   "reqd": 0,
   "search_index": 0,
   "sort_options": 0,
   "translatable": 0,
   "unique": 0,
   "width": null
  },
  {
   "_assign": null,
   "_comments": null,
   "_liked_by": null,
   "_user_tags": null,
   "allow_in_quick_entry": 0,
   "allow_on_submit": 0,
   "bold": 0,
   "collapsible": 0,
   "collapsible_depends_on": null,
   "columns": 0,
   "creation": "2023-09-20 19:02:36.872215",
   "default": null,
   "depends_on": "",
   "description": null,
   "docstatus": 0,
   "dt": "Stock Entry",
   "fetch_from": null,
   "fetch_if_empty": 0,
   "fieldname": "total_qty",
   "fieldtype": "Float",
   "hidden": 0,
   "hide_border": 0,
   "hide_days": 0,
   "hide_seconds": 0,
   "idx": 57,
   "ignore_user_permissions": 0,
   "ignore_xss_filter": 0,
   "in_global_search": 0,
   "in_list_view": 0,
   "in_preview": 0,
   "in_standard_filter": 0,
   "insert_after": "column_break_22",
   "is_system_generated": 0,
   "is_virtual": 0,
   "label": "Total Qty",
   "length": 0,
   "mandatory_depends_on": null,
   "modified": "2023-09-20 19:02:36.872215",
   "modified_by": "Administrator",
   "module": null,
   "name": "Stock Entry-total_qty",
   "no_copy": 0,
   "non_negative": 0,
   "options": null,
   "owner": "Administrator",
   "permlevel": 0,
   "precision": "",
   "print_hide": 0,
   "print_hide_if_no_value": 0,
   "print_width": null,
   "read_only": 1,
   "read_only_depends_on": null,
   "report_hide": 0,
   "reqd": 0,
   "search_index": 0,
   "sort_options": 0,
   "translatable": 0,
   "unique": 0,
   "width": null
  }
 ],
 "custom_perms": [
  {
   "_assign": null,
   "_comments": null,
   "_liked_by": null,
   "_user_tags": null,
   "amend": 1,
   "cancel": 1,
   "create": 1,
   "creation": "2023-05-16 16:11:54.432142",
   "delete": 1,
   "docstatus": 0,
   "email": 1,
   "export": 0,
   "idx": 3,
   "if_owner": 0,
   "import": 0,
   "modified": "2023-05-16 16:11:54.432142",
   "modified_by": "Administrator",
   "name": "c1065f5df5",
   "owner": "Administrator",
   "parent": "Stock Entry",
   "permlevel": 0,
   "print": 1,
   "read": 1,
   "report": 1,
   "role": "Manufacturing Manager",
   "select": 0,
   "set_user_permissions": 0,
   "share": 1,
   "submit": 1,
   "write": 1
  },
  {
   "_assign": null,
   "_comments": null,
   "_liked_by": null,
   "_user_tags": null,
   "amend": 1,
   "cancel": 1,
   "create": 1,
   "creation": "2023-05-16 16:11:54.487146",
   "delete": 1,
   "docstatus": 0,
   "email": 1,
   "export": 1,
   "idx": 4,
   "if_owner": 0,
   "import": 1,
   "modified": "2023-05-16 16:11:54.487146",
   "modified_by": "Administrator",
   "name": "efb9f62270",
   "owner": "Administrator",
   "parent": "Stock Entry",
   "permlevel": 0,
   "print": 1,
   "read": 1,
   "report": 1,
   "role": "Stock Manager",
   "select": 0,
   "set_user_permissions": 1,
   "share": 1,
   "submit": 1,
   "write": 1
  },
  {
   "_assign": null,
   "_comments": null,
   "_liked_by": null,
   "_user_tags": null,
   "amend": 1,
   "cancel": 1,
   "create": 1,
   "creation": "2023-05-16 16:11:54.521480",
   "delete": 1,
   "docstatus": 0,
   "email": 1,
   "export": 0,
   "idx": 1,
   "if_owner": 0,
   "import": 0,
   "modified": "2023-05-16 16:11:54.521480",
   "modified_by": "Administrator",
   "name": "6a43506911",
   "owner": "Administrator",
   "parent": "Stock Entry",
   "permlevel": 0,
   "print": 1,
   "read": 1,
   "report": 1,
   "role": "Stock User",
   "select": 0,
   "set_user_permissions": 0,
   "share": 1,
   "submit": 1,
   "write": 1
  },
  {
   "_assign": null,
   "_comments": null,
   "_liked_by": null,
   "_user_tags": null,
   "amend": 1,
   "cancel": 1,
   "create": 1,
   "creation": "2023-05-16 16:11:54.553978",
   "delete": 1,
   "docstatus": 0,
   "email": 1,
   "export": 0,
   "idx": 2,
   "if_owner": 0,
   "import": 0,
   "modified": "2023-05-16 16:11:54.553978",
   "modified_by": "Administrator",
   "name": "bf62c9591b",
   "owner": "Administrator",
   "parent": "Stock Entry",
   "permlevel": 0,
   "print": 1,
   "read": 1,
   "report": 1,
   "role": "Manufacturing User",
   "select": 0,
   "set_user_permissions": 0,
   "share": 1,
   "submit": 1,
   "write": 1
  },
  {
   "_assign": null,
   "_comments": null,
   "_liked_by": null,
   "_user_tags": null,
   "amend": 1,
   "cancel": 1,
   "create": 1,
   "creation": "2023-05-16 16:11:54.590032",
   "delete": 1,
   "docstatus": 0,
   "email": 0,
   "export": 0,
   "idx": 0,
   "if_owner": 0,
   "import": 0,
   "modified": "2023-05-16 16:11:54.590032",
   "modified_by": "Administrator",
   "name": "083cf5678f",
   "owner": "Administrator",
   "parent": "Stock Entry",
   "permlevel": 0,
   "print": 1,
   "read": 1,
   "report": 1,
   "role": "Unit 2",
   "select": 0,
   "set_user_permissions": 0,
   "share": 0,
   "submit": 1,
   "write": 1
  },
  {
   "_assign": null,
   "_comments": null,
   "_liked_by": null,
   "_user_tags": null,
   "amend": 1,
   "cancel": 0,
   "create": 1,
   "creation": "2023-09-20 10:12:17.354098",
   "delete": 0,
   "docstatus": 0,
   "email": 0,
   "export": 1,
   "idx": 0,
   "if_owner": 0,
   "import": 0,
   "modified": "2023-09-20 10:12:17.354098",
   "modified_by": "Administrator",
   "name": "759adbcb52",
   "owner": "Administrator",
   "parent": "Stock Entry",
   "permlevel": 0,
   "print": 0,
   "read": 1,
   "report": 1,
   "role": "Box Supplier",
   "select": 1,
   "set_user_permissions": 0,
   "share": 0,
   "submit": 1,
   "write": 1
  }
 ],
 "doctype": "Stock Entry",
 "links": [],
 "property_setters": [
  {
   "_assign": null,
   "_comments": null,
   "_liked_by": null,
   "_user_tags": null,
   "creation": "2023-06-07 12:42:42.442885",
   "default_value": null,
   "doc_type": "Stock Entry",
   "docstatus": 0,
   "doctype_or_field": "DocField",
   "field_name": "section_break_jwgn",
   "idx": 0,
   "is_system_generated": 0,
   "modified": "2023-06-07 12:42:42.442885",
   "modified_by": "Administrator",
   "module": null,
   "name": "Stock Entry-section_break_jwgn-depends_on",
   "owner": "Administrator",
   "property": "depends_on",
   "property_type": "Data",
   "row_name": null,
   "value": ""
  },
  {
   "_assign": null,
   "_comments": null,
   "_liked_by": null,
   "_user_tags": null,
   "creation": "2023-06-07 12:42:20.549638",
   "default_value": null,
   "doc_type": "Stock Entry",
   "docstatus": 0,
   "doctype_or_field": "DocField",
   "field_name": "other_info_tab",
   "idx": 0,
   "is_system_generated": 0,
   "modified": "2023-06-07 12:42:20.549638",
   "modified_by": "Administrator",
   "module": null,
   "name": "Stock Entry-other_info_tab-depends_on",
   "owner": "Administrator",
   "property": "depends_on",
   "property_type": "Data",
   "row_name": null,
   "value": ""
  },
  {
   "_assign": null,
   "_comments": null,
   "_liked_by": null,
   "_user_tags": null,
   "creation": "2023-06-07 12:41:01.785171",
   "default_value": null,
   "doc_type": "Stock Entry",
   "docstatus": 0,
   "doctype_or_field": "DocField",
   "field_name": "accounting_dimensions_section",
   "idx": 0,
   "is_system_generated": 0,
   "modified": "2023-06-07 12:41:01.785171",
   "modified_by": "Administrator",
   "module": null,
   "name": "Stock Entry-accounting_dimensions_section-depends_on",
   "owner": "Administrator",
   "property": "depends_on",
   "property_type": "Data",
   "row_name": null,
   "value": "eval:(frappe.user_roles.includes(\"Unit 2\")  && (doc.stock_entry_type === \"Tank Manufactured\" || doc.stock_entry_type === \"Tank Transferred\"))"
  },
  {
   "_assign": null,
   "_comments": null,
   "_liked_by": null,
   "_user_tags": null,
   "creation": "2023-06-07 12:39:05.791392",
   "default_value": null,
   "doc_type": "Stock Entry",
   "docstatus": 0,
   "doctype_or_field": "DocField",
   "field_name": "to_warehouse",
   "idx": 0,
   "is_system_generated": 0,
   "modified": "2023-06-07 12:39:05.791392",
   "modified_by": "Administrator",
   "module": null,
   "name": "Stock Entry-to_warehouse-read_only_depends_on",
   "owner": "Administrator",
   "property": "read_only_depends_on",
   "property_type": "Data",
   "row_name": null,
   "value": "eval:(frappe.user_roles.includes(\"Unit 2\")  && (doc.stock_entry_type === \"Tank Manufactured\" || doc.stock_entry_type === \"Tank Transferred\"))"
  },
  {
   "_assign": null,
   "_comments": null,
   "_liked_by": null,
   "_user_tags": null,
   "creation": "2023-06-07 11:44:15.364928",
   "default_value": null,
   "doc_type": "Stock Entry",
   "docstatus": 0,
   "doctype_or_field": "DocField",
   "field_name": "from_warehouse",
   "idx": 0,
   "is_system_generated": 0,
   "modified": "2023-06-07 11:44:15.364928",
   "modified_by": "Administrator",
   "module": null,
   "name": "Stock Entry-from_warehouse-read_only_depends_on",
   "owner": "Administrator",
   "property": "read_only_depends_on",
   "property_type": "Data",
   "row_name": null,
   "value": "eval:(frappe.user_roles.includes(\"Unit 2\")  && (doc.stock_entry_type === \"Tank Manufactured\" || doc.stock_entry_type === \"Tank Transferred\"))"
  },
  {
   "_assign": null,
   "_comments": null,
   "_liked_by": null,
   "_user_tags": null,
   "creation": "2023-06-07 11:36:53.252787",
   "default_value": null,
   "doc_type": "Stock Entry",
   "docstatus": 0,
   "doctype_or_field": "DocField",
   "field_name": "section_break_jwgn",
   "idx": 0,
   "is_system_generated": 0,
   "modified": "2023-06-07 11:36:53.252787",
   "modified_by": "Administrator",
   "module": null,
   "name": "Stock Entry-section_break_jwgn-collapsible",
   "owner": "Administrator",
   "property": "collapsible",
   "property_type": "Check",
   "row_name": null,
   "value": "0"
  },
  {
   "_assign": null,
   "_comments": null,
   "_liked_by": null,
   "_user_tags": null,
   "creation": "2023-06-07 11:36:32.701435",
   "default_value": null,
   "doc_type": "Stock Entry",
   "docstatus": 0,
   "doctype_or_field": "DocField",
   "field_name": "bom_info_section",
   "idx": 0,
   "is_system_generated": 0,
   "modified": "2023-06-07 11:36:32.701435",
   "modified_by": "Administrator",
   "module": null,
   "name": "Stock Entry-bom_info_section-hidden",
   "owner": "Administrator",
   "property": "hidden",
   "property_type": "Check",
   "row_name": null,
   "value": "1"
  },
  {
   "_assign": null,
   "_comments": null,
   "_liked_by": null,
   "_user_tags": null,
   "creation": "2023-05-22 12:15:55.038457",
   "default_value": null,
   "doc_type": "Stock Entry",
   "docstatus": 0,
   "doctype_or_field": "DocField",
   "field_name": "from_warehouse",
   "idx": 0,
   "is_system_generated": 1,
   "modified": "2023-06-05 06:46:57.641302",
   "modified_by": "Administrator",
   "module": null,
   "name": "Stock Entry-from_warehouse-in_list_view",
   "owner": "Administrator",
   "property": "in_list_view",
   "property_type": "Check",
   "row_name": null,
   "value": "1"
  },
  {
   "_assign": null,
   "_comments": null,
   "_liked_by": null,
   "_user_tags": null,
   "creation": "2023-05-22 12:15:55.019275",
   "default_value": null,
   "doc_type": "Stock Entry",
   "docstatus": 0,
   "doctype_or_field": "DocField",
   "field_name": "to_warehouse",
   "idx": 0,
   "is_system_generated": 1,
   "modified": "2023-06-05 06:46:57.614388",
   "modified_by": "Administrator",
   "module": null,
   "name": "Stock Entry-to_warehouse-in_list_view",
   "owner": "Administrator",
   "property": "in_list_view",
   "property_type": "Check",
   "row_name": null,
   "value": "1"
  },
  {
   "_assign": null,
   "_comments": null,
   "_liked_by": null,
   "_user_tags": null,
   "creation": "2023-05-22 12:15:55.057659",
   "default_value": null,
   "doc_type": "Stock Entry",
   "docstatus": 0,
   "doctype_or_field": "DocField",
   "field_name": "stock_entry_type",
   "idx": 0,
   "is_system_generated": 1,
   "modified": "2023-06-05 06:46:57.562453",
   "modified_by": "Administrator",
   "module": null,
   "name": "Stock Entry-stock_entry_type-in_list_view",
   "owner": "Administrator",
   "property": "in_list_view",
   "property_type": "Check",
   "row_name": null,
   "value": "1"
  },
  {
   "_assign": null,
   "_comments": null,
   "_liked_by": null,
   "_user_tags": null,
   "creation": "2023-06-05 06:45:15.651846",
   "default_value": null,
   "doc_type": "Stock Entry",
   "docstatus": 0,
   "doctype_or_field": "DocField",
   "field_name": "source_warehouse_address",
   "idx": 0,
   "is_system_generated": 1,
   "modified": "2023-06-05 06:46:17.450922",
   "modified_by": "Administrator",
   "module": null,
   "name": "Stock Entry-source_warehouse_address-in_list_view",
   "owner": "Administrator",
   "property": "in_list_view",
   "property_type": "Check",
   "row_name": null,
   "value": "0"
  },
  {
   "_assign": null,
   "_comments": null,
   "_liked_by": null,
   "_user_tags": null,
   "creation": "2023-05-22 12:16:41.974792",
   "default_value": null,
   "doc_type": "Stock Entry",
   "docstatus": 0,
   "doctype_or_field": "DocField",
   "field_name": "entry_date",
   "idx": 0,
   "is_system_generated": 1,
   "modified": "2023-06-05 06:43:55.916158",
   "modified_by": "Administrator",
   "module": null,
   "name": "Stock Entry-entry_date-in_list_view",
   "owner": "Administrator",
   "property": "in_list_view",
   "property_type": "Check",
   "row_name": null,
   "value": "0"
  },
  {
   "_assign": null,
   "_comments": null,
   "_liked_by": null,
   "_user_tags": null,
   "creation": "2023-05-22 12:15:55.074885",
   "default_value": null,
   "doc_type": "Stock Entry",
   "docstatus": 0,
   "doctype_or_field": "DocField",
   "field_name": "purpose",
   "idx": 0,
   "is_system_generated": 1,
   "modified": "2023-05-22 12:16:41.876812",
   "modified_by": "Administrator",
   "module": null,
   "name": "Stock Entry-purpose-in_list_view",
   "owner": "Administrator",
   "property": "in_list_view",
   "property_type": "Check",
   "row_name": null,
   "value": "0"
  },
  {
   "_assign": null,
   "_comments": null,
   "_liked_by": null,
   "_user_tags": null,
   "creation": "2023-05-22 12:15:55.088545",
   "default_value": null,
   "doc_type": "Stock Entry",
   "docstatus": 0,
   "doctype_or_field": "DocField",
   "field_name": "is_return",
   "idx": 0,
   "is_system_generated": 1,
   "modified": "2023-05-22 12:16:41.806259",
   "modified_by": "Administrator",
   "module": null,
   "name": "Stock Entry-is_return-in_list_view",
   "owner": "Administrator",
   "property": "in_list_view",
   "property_type": "Check",
   "row_name": null,
   "value": "0"
  },
  {
   "_assign": null,
   "_comments": null,
   "_liked_by": null,
   "_user_tags": null,
   "creation": "2023-05-22 12:15:54.983135",
   "default_value": null,
   "doc_type": "Stock Entry",
   "docstatus": 0,
   "doctype_or_field": "DocField",
   "field_name": "per_transferred",
   "idx": 0,
   "is_system_generated": 1,
   "modified": "2023-05-22 12:15:54.983135",
   "modified_by": "Administrator",
   "module": null,
   "name": "Stock Entry-per_transferred-in_list_view",
   "owner": "Administrator",
   "property": "in_list_view",
   "property_type": "Check",
   "row_name": null,
   "value": "0"
  },
  {
   "_assign": null,
   "_comments": null,
   "_liked_by": null,
   "_user_tags": null,
   "creation": "2023-05-16 15:26:42.894290",
   "default_value": null,
   "doc_type": "Stock Entry",
   "docstatus": 0,
   "doctype_or_field": "DocField",
   "field_name": "section_break_jwgn",
   "idx": 0,
   "is_system_generated": 0,
   "modified": "2023-05-16 15:26:42.894290",
   "modified_by": "Administrator",
   "module": null,
   "name": "Stock Entry-section_break_jwgn-read_only_depends_on",
   "owner": "Administrator",
   "property": "read_only_depends_on",
   "property_type": "Data",
   "row_name": null,
   "value": "eval:doc.company==\"Red Star Unit 2\""
  },
  {
   "_assign": null,
   "_comments": null,
   "_liked_by": null,
   "_user_tags": null,
   "creation": "2023-05-12 10:15:39.184560",
   "default_value": null,
   "doc_type": "Stock Entry",
   "docstatus": 0,
   "doctype_or_field": "DocField",
   "field_name": "scan_barcode",
   "idx": 0,
   "is_system_generated": 1,
   "modified": "2023-05-12 10:15:39.184560",
   "modified_by": "Administrator",
   "module": null,
   "name": "Stock Entry-scan_barcode-hidden",
   "owner": "Administrator",
   "property": "hidden",
   "property_type": "Check",
   "row_name": null,
   "value": "1"
  },
  {
   "_assign": null,
   "_comments": null,
   "_liked_by": null,
   "_user_tags": null,
   "creation": "2023-04-13 16:16:08.262257",
   "default_value": null,
   "doc_type": "Stock Entry",
   "docstatus": 0,
   "doctype_or_field": "DocType",
   "field_name": null,
   "idx": 0,
   "is_system_generated": 1,
   "modified": "2023-04-13 16:16:08.262257",
   "modified_by": "Administrator",
   "module": null,
   "name": "Stock Entry-main-track_changes",
   "owner": "Administrator",
   "property": "track_changes",
   "property_type": "Check",
   "row_name": null,
   "value": "1"
  }
 ],
 "sync_on_migrate": 1
}